redfish_utilities/__init__.py
redfish_utilities/accounts.py
redfish_utilities/assembly.py
redfish_utilities/certificates.py
redfish_utilities/collections.py
redfish_utilities/config.py
redfish_utilities/event_service.py
redfish_utilities/inventory.py
redfish_utilities/licenses.py
redfish_utilities/logs.py
redfish_utilities/managers.py
redfish_utilities/messages.py
redfish_utilities/misc.py
redfish_utilities/power_equipment.py
redfish_utilities/resets.py
redfish_utilities/sensors.py
redfish_utilities/systems.py
redfish_utilities/tasks.py
redfish_utilities/thermal_equipment.py
redfish_utilities/update.py
redfish_utilities-3.4.3.data/scripts/rf_accounts.py
redfish_utilities-3.4.3.data/scripts/rf_assembly.py
redfish_utilities-3.4.3.data/scripts/rf_bios_settings.py
redfish_utilities-3.4.3.data/scripts/rf_boot_override.py
redfish_utilities-3.4.3.data/scripts/rf_certificates.py
redfish_utilities-3.4.3.data/scripts/rf_diagnostic_data.py
redfish_utilities-3.4.3.data/scripts/rf_discover.py
redfish_utilities-3.4.3.data/scripts/rf_event_service.py
redfish_utilities-3.4.3.data/scripts/rf_firmware_inventory.py
redfish_utilities-3.4.3.data/scripts/rf_licenses.py
redfish_utilities-3.4.3.data/scripts/rf_logs.py
redfish_utilities-3.4.3.data/scripts/rf_manager_config.py
redfish_utilities-3.4.3.data/scripts/rf_power_equipment.py
redfish_utilities-3.4.3.data/scripts/rf_power_reset.py
redfish_utilities-3.4.3.data/scripts/rf_raw_request.py
redfish_utilities-3.4.3.data/scripts/rf_sel.py
redfish_utilities-3.4.3.data/scripts/rf_sensor_list.py
redfish_utilities-3.4.3.data/scripts/rf_sys_inventory.py
redfish_utilities-3.4.3.data/scripts/rf_test_event_listener.py
redfish_utilities-3.4.3.data/scripts/rf_thermal_equipment.py
redfish_utilities-3.4.3.data/scripts/rf_update.py
redfish_utilities-3.4.3.data/scripts/rf_virtual_media.py
redfish_utilities-3.4.3.dist-info/licenses/AUTHORS.md
redfish_utilities-3.4.3.dist-info/licenses/LICENSE.md
redfish_utilities-3.4.3.dist-info/METADATA
redfish_utilities-3.4.3.dist-info/WHEEL
redfish_utilities-3.4.3.dist-info/top_level.txt
redfish_utilities-3.4.3.dist-info/RECORD
