Metadata-Version: 2.4
Name: redfish_utilities
Version: 3.4.3
Summary: Redfish Utilities
Home-page: https://github.com/DMTF/Redfish-Tacklebox
Author: DMTF, https://www.dmtf.org/standards/feedback
License: BSD 3-clause "New" or "Revised License"
Keywords: Redfish
Classifier: Development Status :: 5 - Production/Stable
Classifier: License :: OSI Approved :: BSD License
Classifier: Programming Language :: Python :: 3
Classifier: Topic :: Communications
License-File: LICENSE.md
License-File: AUTHORS.md
Requires-Dist: redfish>=3.2.1
Requires-Dist: XlsxWriter>=1.2.7
Requires-Dist: requests
Dynamic: author
Dynamic: classifier
Dynamic: description
Dynamic: description-content-type
Dynamic: home-page
Dynamic: keywords
Dynamic: license
Dynamic: license-file
Dynamic: requires-dist
Dynamic: summary
